aws_recommendation_a12/__init__.py
aws_recommendation_a12/cloudwatch.py
aws_recommendation_a12/cost_estimations.py
aws_recommendation_a12/dynamodb.py
aws_recommendation_a12/ebs.py
aws_recommendation_a12/ec2.py
aws_recommendation_a12/elb.py
aws_recommendation_a12/kms.py
aws_recommendation_a12/rds.py
aws_recommendation_a12/recommendation.py
aws_recommendation_a12/redshift.py
aws_recommendation_a12/s3.py
aws_recommendation_a12/truted_advisor.py
aws_recommendation_a12/utils.py
aws_recommendation_a12-0.0.24.dist-info/LICENCE
aws_recommendation_a12-0.0.24.dist-info/METADATA
aws_recommendation_a12-0.0.24.dist-info/WHEEL
aws_recommendation_a12-0.0.24.dist-info/top_level.txt
aws_recommendation_a12-0.0.24.dist-info/RECORD
